akxtest/__init__.py
akxtest/akxtest.py
akxtest-1.0.0.dist-info/METADATA
akxtest-1.0.0.dist-info/WHEEL
akxtest-1.0.0.dist-info/entry_points.txt
akxtest-1.0.0.dist-info/top_level.txt
akxtest-1.0.0.dist-info/RECORD
